{"JOB DESCRIPTION": " We are looking for an ASP.NET MVC developer that will be able to develop applications.  The main scope of work will include everything from back - end to client - side code, using optimal and efficient technologies, frameworks, and patterns.   Experience:   2 - 6 years   Responsibilities:     The primary responsibilities will be to design and develop these applications.    Integrating with front - end developers & Delivering a high - quality application.    Writing test - backed server - side code.    Analyzing requirements and designing new functionality.    Supporting and fixing existing functionality.    Selecting and using the most appropriate and efficient technologies for a particular application.    Knowledge in Responsive Web Designing using Bootstrap CSS & Extensive Knowledge on Microsoft Visual Studio 2017   Required Candidate profile:     Threshold competencies: Any BCAB.TECH(ITCS) graduate or related stream with relevant years - of experience in building web based .NET applicationsweb services is desirable.    Technical Competencies: Excellent knowledge & experience of multiple technologies like .NET 4.6, ASP.NET MVC, CSS, C# .NET, AJAX, JQuery, AngularJS, ADO .NET, Entity Framework, WEB API, Lamda expressions, LINQ, LINQ with SQL, Azure SQLSQL Server 201416, MongoDB is must Knowledge of working on Microsoft Azure PaaS platform will be a plus point (App Services, Azure SQL)   Perks and Benefits    Best in the industry   Role:   Software Developer   Industry Type:   IT - Software Software Services   Functional Area:   IT Software - Application Programming, Maintenance   Employment Type:   Full Time, Permanent   Role Category:   Programming & Design   Education     UG:   BCA in Computers, B.TechB.E. in Any Specialization, Computers   PG:   MCA in Computers, M.Tech in Computers, Any Specialization   Doctorate:   Any Doctorate in Any Specialization, Doctorate Not Required   Key Skills    WEB API, AngularJS, CSS, ASP.NET, MVCSQL, JQuery, Azure, SQL Server, .Net, MongoDB, Entity Framework, C# .NET, AJAX, ADO .NET                                                  ", "ROLE": "Software Developer", "INDUSTRY TYPE": "IT-Software, Software Services", "FUNCTIONAL AREA": "IT Software - Application Programming, Maintenance", "EMPLOYMENT TYPE": "Full Time, Permanen", "ROLE CATEGORY": "Programming & Desig", "EDUCATION": {"UG": "Any Graduate in Any Specialization", "PG": "Post Graduation Not Required"}, "KEY SKILL": ["jQuery", "LINQ", "Front end", "Application programming", "PAAS", "Entity framework", "MongoDB", "Visual Studio", "Software services", "Ajax"]}