{"JOB DESCRIPTION": "Senior Software Engineer FrontendEducation : B.E. Computer Science/IT degree (or any other engineering discipline) | PG in Computer ApplicationsExperience: 3+ years experience in Frontend technologies & Minimum 1 year hands on experience in Vue.Js & JqueryPosition Requirement : We are looking for an expert JavaScript developer who is highly skilled with Vue.js. Your primary focus will be developing user-facing web applications and components. Youll implement them with the Vue.js framework, following generally accepted practices and workflows. You will ensure that you produce robust, secure, modular, and maintainable code. Your commitment to team a quality product is crucial.- Highly proficient with Vue.js framework and its core principles such as components, reactivity, and the virtual DOM.- Familiarity with the Vue.js ecosystem.- Familiarity with the Jquery.- Highly proficient with the JavaScript, Node JS.- Good understanding of HTML5 and CSS3.- Understanding of server-side rendering and its benefits and use cases.- Ability to write efficient, secure, well-documented, and clean JavaScript code.Role & Responsibility:- Developing user-facing applications using Vue.js.- Building modular and reusable components and libraries.- Optimizing your application for performance.- Individual must be a self-starter with the ability to handle number of simultaneous projects, demonstrate a sense of urgency and ownership to drive projects to completion and be successful in a collaborative environment.Role: Software DeveloperIndustry Type: IT-Software, Software ServicesFunctional Area: IT Software - OtherEmployment Type:Full Time, PermanentRole Category: Programming & DesignEducationUG :B.Tech/B.E. in Any Specialization | PG in Any SpecializationKey Skillsvue js, javascriptcss, html5, vue, ES6, jquery, css3", "ROLE": "Software Developer", "INDUSTRY TYPE": "IT-Software, Software Services", "FUNCTIONAL AREA": "IT Software - Other", "EMPLOYMENT TYPE": "Full Time, Permanen", "ROLE CATEGORY": "Programming & Desig", "EDUCATION": {"UG": "B.Tech/B.E. in Any Specialization"}, "KEY SKILL": ["Vue.Js", "Javascript", "JQuery", "Software Development", "Front End", "Html5", "Web Technologies", "Vue", "Es6"]}